[
  {
    "id": 0,
    "question": "프로세스와 스레드의 차이는 무엇인가요?",
    "answer": "쉽게 비유하면, **프로세스**는 각각 독립된 사무실이고 **스레드**는 같은 사무실 안의 팀원이에요.\n\n**프로세스**는 운영체제가 프로그램을 실행할 때 만드는 독립된 실행 단위입니다. 실행 중인 프로그램 하나하나가 프로세스이고, 각각 자기만의 메모리 공간(**코드**, **데이터**, **힙**, **스택**)을 갖고 있어요. 사무실이 독립되어 있으니까 한 프로세스가 죽어도 다른 프로세스에는 직접적인 영향이 적습니다.\n\n**스레드**는 프로세스 내부에서 실제로 작업을 수행하는 실행 흐름 단위예요. 같은 프로세스 안의 스레드끼리는 **코드 영역, 힙, 데이터 영역을 공유**하면서 **스택만 개별**로 갖습니다. 같은 사무실의 팀원처럼 자원을 공유하니 통신이 빠르지만, 같은 데이터를 동시에 건드리면 충돌이 생기기 쉬워요.\n\n```\n Process A          Process B\n ┌──────────┐      ┌──────────┐\n │Code,Data │      │Code,Data │\n │  Heap    │      │  Heap    │\n │ T1  T2   │      │ T1       │\n │(stk)(stk)│      │(stk)     │\n └──────────┘      └──────────┘\n 스레드는 힙 공유, 스택은 별도\n```\n\n프론트엔드에서 이게 왜 중요하냐면, 브라우저는 내부적으로 **렌더링, 네트워크, JS 실행, GPU 처리** 같은 여러 계층으로 동작하거든요. 특히 **브라우저 탭** 하나가 기본적으로 별도 프로세스이고, 그 안의 **메인 스레드 하나**에서 JavaScript 실행과 DOM 조작이 모두 처리됩니다. 그래서 메인 스레드에서 무거운 연산을 돌리면 UI가 멈추는 거예요. **Web Worker**를 쓰면 별도 스레드에서 JS를 실행할 수 있지만 DOM에는 접근할 수 없습니다."
  },
  {
    "id": 1,
    "question": "멀티프로세스와 멀티스레드의 장단점을 비교해주세요.",
    "answer": "핵심만 말하면, **멀티프로세스는 안정성**, **멀티스레드는 효율성**이 강점이에요.\n\n### 멀티프로세스\n\n프로세스마다 메모리가 분리돼 있어서 **격리**가 좋습니다. 한 프로세스가 죽어도 다른 프로세스에 영향이 적고, 보안 측면에서도 유리해요. 대신 프로세스 생성 비용이 크고, 프로세스 간 통신(**IPC**)도 상대적으로 무거우며, **컨텍스트 스위칭** 비용이 큽니다.\n\n### 멀티스레드\n\n같은 프로세스의 메모리를 공유하니까 생성이 가볍고 통신도 빨라요. 하지만 같은 메모리를 동시에 다루기 때문에 **race condition**, **deadlock** 같은 동기화 문제가 생기기 쉽고, 한 스레드의 버그가 전체 프로세스에 영향을 줄 수 있습니다.\n\n| | 멀티프로세스 | 멀티스레드 |\n|---|---|---|\n| **메모리** | 독립 (격리) | 공유 (효율) |\n| **안정성** | 높음 | 상대적으로 낮음 |\n| **통신** | IPC (무거움) | 메모리 공유 (빠름) |\n| **동기화 문제** | 적음 | race condition, deadlock 위험 |\n\n이걸 왜 알아야 하냐면, **Node.js**가 대표적인 예입니다. JS 실행 자체는 단일 스레드처럼 보이지만, 내부적으로 **libuv**, **worker threads**, OS 수준 비동기 I/O가 맞물려 동작해요. 왜 어떤 작업은 메인 스레드를 막는지 이해하려면 이 감각이 필요합니다."
  },
  {
    "id": 2,
    "question": "동기와 비동기의 차이를 설명해주세요.",
    "answer": "**동기**는 요청한 작업이 끝나야 다음 줄로 넘어가는 방식이에요. 결과가 돌아올 때까지 기다립니다. **비동기**는 작업을 요청한 뒤 완료를 기다리지 않고 다른 작업을 진행하는 방식이고, 결과는 나중에 **callback**, **Promise**, **await** 같은 메커니즘으로 이어받아요.\n\n여기서 정말 중요한 포인트가 하나 있는데, **\"동기가 느리고 비동기가 빠르다\"는 이해는 틀렸다**는 거예요. 핵심은 속도가 아니라 **완료 시점과 제어 흐름이 어떻게 연결되느냐**의 차이입니다.\n\n```\n동기 (Synchronous):\n 요청 ──→ [대기...] ──→ 응답 ──→ 다음 작업\n\n비동기 (Asynchronous):\n 요청 ──→ 다음 작업 진행\n          ↑\n          └── 나중에 응답 도착 시 콜백 실행\n```\n\n프론트엔드에서는 네트워크 요청, 타이머, 사용자 입력 처리 등 대부분의 외부 작업을 비동기로 다뤄야 해요. API 호출을 동기적으로 처리하면 응답이 올 때까지 화면이 멈추니까요.\n\n`const data = await fetch('/api')` 같은 코드가 겉보기엔 동기처럼 읽히지만, 실제로는 비동기입니다. **await**가 있다고 작업 자체가 동기가 되는 게 아니라, 해당 함수 내부의 흐름만 중단했다가 결과를 받아 이어가는 것이에요."
  },
  {
    "id": 3,
    "question": "블로킹과 논블로킹의 차이를 설명해주세요.",
    "answer": "**블로킹**은 작업을 요청한 쪽이 끝날 때까지 **제어권을 돌려받지 못하는** 방식이고, **논블로킹**은 요청 후 **바로 제어권을 돌려받아** 다른 작업을 계속할 수 있는 방식이에요.\n\n동기/비동기와 비슷해 보이지만 **다른 축의 개념**입니다:\n\n| | 동기/비동기 | 블로킹/논블로킹 |\n|---|---|---|\n| **관심사** | 완료 시점과 흐름의 연결 | 제어권을 바로 돌려주느냐 |\n| **질문** | \"결과를 언제 받나?\" | \"기다리는 동안 뭘 할 수 있나?\" |\n\n프론트엔드에서 이 구분이 중요한 이유는 **메인 스레드**와 직접 연결되기 때문이에요. 메인 스레드에서 무거운 계산을 돌리면 JS는 사실상 블로킹 상태가 됩니다. 사용자가 버튼 클릭도 못 하고 스크롤도 버벅이게 되죠.\n\n비동기 API를 호출해도 체감상 로딩 스피너만 계속 돌고 아무 상호작용이 안 되면, UX 관점에서는 블로킹처럼 느껴질 수 있어요. 브라우저에서는 **\"메인 스레드를 막는가\"**가 성능의 핵심 기준입니다."
  },
  {
    "id": 4,
    "question": "데드락의 발생 조건 4가지를 설명해주세요.",
    "answer": "**데드락(Deadlock)**은 두 개 이상의 작업이 서로가 가진 자원을 기다리면서 영원히 멈추는 상태예요. 식당에서 두 사람이 각자 젓가락 하나씩을 들고 \"상대방 것을 줘야 식사를 시작한다\"고 버티는 상황과 비슷합니다.\n\n고전적인 발생 조건은 **네 가지**이고, 이 조건이 **동시에** 성립할 때 데드락이 발생합니다:\n\n1. **상호 배제** — 자원을 한 번에 하나의 프로세스만 사용할 수 있음\n2. **점유 대기** — 이미 자원을 가진 상태에서 다른 자원을 기다림\n3. **비선점** — 다른 프로세스가 가진 자원을 강제로 빼앗을 수 없음\n4. **순환 대기** — A는 B를 기다리고, B는 C를 기다리고, C는 다시 A를 기다리는 원형 고리\n\n핵심은 **하나라도 깨뜨리면 데드락을 방지**할 수 있다는 점이에요. 실무에서는 자원 획득 순서를 강제해서 순환 대기를 깨거나, **timeout**을 둬서 점유 대기를 깨는 방식으로 회피합니다.\n\n프론트엔드에서 직접 데드락을 경험할 일은 드물지만, 비동기 흐름에서 서로의 완료를 기다리는 순환 구조가 생기면 비슷한 교착 상태가 발생할 수 있어요."
  },
  {
    "id": 5,
    "question": "Race Condition이 무엇이고, 프론트엔드에서 어떻게 발생하나요?",
    "answer": "**Race Condition**은 여러 작업이 같은 상태나 자원에 접근할 때, **실행 순서에 따라 결과가 달라지는** 문제입니다. 프론트엔드에서 정말 자주 발생해요.\n\n### 대표적인 사례: 검색 자동완성\n\n```\n사용자 입력 \"a\"  → 요청 A 전송\n사용자 입력 \"ab\" → 요청 B 전송\n\n요청 B 응답 도착 → UI에 \"ab\" 결과 표시 ✅\n요청 A 응답 도착 (늦게) → UI에 \"a\" 결과가 덮어씀 ❌\n```\n\n사용자는 \"ab\"를 입력했는데 화면에는 \"a\" 결과가 보이는 거예요. 네트워크 지연 때문에 오래된 응답이 최신 UI를 덮어써버리는 겁니다.\n\n### 프론트엔드에서 흔한 race condition 패턴\n\n- 탭 전환 중 API 응답 순서가 꼬이는 경우\n- 버튼 중복 클릭으로 요청이 중복되는 경우\n- **optimistic update** 후 rollback 타이밍이 꼬이는 경우\n\n### 방어 방법\n\n- **AbortController**로 이전 요청을 취소\n- 요청에 식별자를 붙여 최신 요청만 반영\n- 중복 클릭 방지 로직(디바운스, 버튼 비활성화)\n\n```js\n// AbortController로 이전 요청 취소\nconst controller = new AbortController();\nfetch('/api/search?q=ab', { signal: controller.signal });\n// 새 요청이 나갈 때 이전 것을 취소\ncontroller.abort();\n```\n\n이 개념을 모르면 \"가끔 이상하게 옛날 데이터가 보여요\" 같은 버그를 설명하기 어렵습니다."
  },
  {
    "id": 6,
    "question": "메모리 영역(코드, 스택, 힙, 데이터)을 설명해주세요.",
    "answer": "프로그램이 실행될 때 메모리는 크게 **네 영역**으로 나뉩니다.\n\n```\n ┌─ Stack ↓ ─┐ 지역 변수, 함수 호출 (LIFO, 자동 해제)\n │            │\n │  (free)    │\n │            │\n ├─ Heap  ↑ ─┤ 동적 객체 (GC가 관리)\n ├─ Data ────┤ 전역 변수, 정적 데이터\n └─ Code ────┘ 실행 명령어 (읽기 전용)\n```\n\n- **코드 영역**: 실행할 명령어가 저장되는 곳. 보통 읽기 전용이에요.\n- **데이터 영역**: 전역 변수나 정적 데이터가 저장됩니다.\n- **스택**: 함수 호출 정보와 지역 변수가 쌓이는 공간. **LIFO** 구조로 함수 호출 시 프레임이 push되고 종료 시 pop돼요. 빠르지만 크기가 제한적입니다.\n- **힙**: 런타임에 동적으로 할당되는 객체들이 저장되는 공간. 유연하지만 참조 관리와 **GC(가비지 컬렉션)**가 중요해요.\n\n### 프론트엔드와 연결하면\n\n- 재귀 호출이 너무 깊으면 스택을 초과해서 **stack overflow**가 발생\n- 객체 참조를 끊지 않으면 힙 메모리가 계속 증가\n- 이벤트 리스너나 **클로저**가 큰 객체를 계속 참조하면 힙이 정리되지 않음\n\n이런 문제를 진단하려면 메모리 영역의 특성을 이해하는 게 기본이에요. Chrome DevTools의 Memory 패널에서 힙 스냅샷을 찍어보면 실제로 어떤 객체들이 메모리를 차지하고 있는지 확인할 수 있습니다."
  },
  {
    "id": 7,
    "question": "가비지 컬렉션이 무엇이고, JavaScript에서 메모리 누수는 왜 발생하나요?",
    "answer": "**GC(Garbage Collection)**는 더 이상 사용할 수 없는 메모리를 자동으로 회수하는 메커니즘입니다. JavaScript 엔진은 **루트 객체**(전역 객체, 현재 실행 중인 함수의 변수 등)에서 출발해서 **도달 가능한(reachable)** 객체만 살려두고, 도달할 수 없는 객체를 수거해요.\n\n핵심은 \"GC가 알아서 해준다\"가 아니라, **\"참조가 남으면 치우지 못한다\"**는 거예요.\n\n### 흔한 메모리 누수 패턴\n\n| 패턴 | 설명 |\n|---|---|\n| **이벤트 리스너 미해제** | window에 리스너를 달고 안 지우면 계속 유지 |\n| **클로저가 큰 객체 참조** | 함수가 큰 데이터를 캡처한 채 해제 안 됨 |\n| **분리된 DOM 노드** | DOM에서 제거했지만 JS 변수가 여전히 참조 |\n| **캐시 무한 증가** | Map이나 배열에 push만 하고 정리 안 함 |\n| **타이머 미정리** | setInterval을 걸어놓고 clearInterval 안 함 |\n\n```js\n// 누수 예시 — 컴포넌트가 언마운트돼도 리스너가 남음\nuseEffect(() => {\n  const handler = () => { /* ... */ };\n  window.addEventListener('resize', handler);\n  // cleanup 빠짐! → 누수\n  return () => window.removeEventListener('resize', handler); // 이게 필요\n}, []);\n```\n\nGC 알고리즘 이름을 길게 말하는 것보다, **도달 가능성**과 참조 유지를 정확히 설명하는 게 면접에서 더 중요합니다. 실무에서는 Chrome DevTools의 **Heap Snapshot**이나 **Allocation Timeline**으로 누수를 추적해요."
  },
  {
    "id": 8,
    "question": "배열과 연결 리스트의 차이를 설명해주세요.",
    "answer": "**배열**은 교실 좌석 번호 같은 거예요. 번호만 알면 바로 찾아갈 수 있습니다. **연결 리스트**는 보물찾기처럼 각 노드가 다음 단서 위치를 가리키는 구조예요.\n\n| | 배열 | 연결 리스트 |\n|---|---|---|\n| **인덱스 접근** | **O(1)** — 바로 찾아감 | **O(n)** — 처음부터 따라가야 함 |\n| **중간 삽입/삭제** | **O(n)** — 나머지를 밀어야 함 | **O(1)** — 포인터만 변경 |\n| **메모리 배치** | 연속 구간 → CPU 캐시 친화적 | 흩어져 있음 → 캐시 locality 약함 |\n| **추가 메모리** | 데이터만 저장 | 노드마다 포인터 저장 필요 |\n\n```\n배열:     [A][B][C][D][E]  ← 연속 메모리\n연결리스트: A→B→C→D→E→null ← 각 노드가 다음을 가리킴\n```\n\n프론트엔드 실무에서는 대부분 **배열**로 충분해요. JavaScript의 Array가 워낙 최적화가 잘 되어 있거든요. 하지만 중요한 건 \"어떤 자료구조가 더 좋다\"가 아니라, **어떤 연산이 자주 필요한지에 따라 선택하는 감각**입니다.\n\n예를 들어 정렬이나 필터를 매 렌더마다 배열 전체를 복사해서 하고 있다면, 그 비용을 의식해야 해요. 가상화(virtualization) 설계에서도 \"보이는 범위만 렌더링한다\"는 판단이 이 감각에서 나옵니다."
  },
  {
    "id": 9,
    "question": "해시 테이블이 무엇이고, 왜 평균 O(1)인가요?",
    "answer": "**해시 테이블**은 키를 **해시 함수**로 변환해서 저장 위치를 직접 찾아가는 자료구조입니다. 도서관의 색인 카드 같은 거예요 — 책 이름을 알면 색인에서 바로 위치를 찾을 수 있죠.\n\n```\n key → hash() → index\n [0] → empty\n [1] → (\"foo\", value)\n [2] → (\"abc\", v1) → (\"xyz\", v2)  ← 충돌! 체이닝으로 해결\n\n 평균 O(1) | 최악 O(n)\n```\n\n평균 **O(1)**인 이유는, 키를 해시 함수에 넣으면 바로 특정 버킷 위치가 나오기 때문에 전체 데이터를 순회할 필요가 없어서예요. 다만 서로 다른 키가 같은 버킷에 매핑되는 **충돌(collision)**이 발생하면 같은 버킷 안에서 비교해야 하니까, 최악의 경우에는 **O(n)**까지 갈 수 있습니다.\n\n### 프론트엔드에서의 활용\n\nJavaScript의 **Object**, **Map**, **Set** 모두 내부적으로 해시 테이블 원리로 동작해요.\n\n```js\n// 배열에서 find → O(n)\nconst user = users.find(u => u.id === targetId);\n\n// Map으로 lookup → O(1)\nconst userMap = new Map(users.map(u => [u.id, u]));\nconst user = userMap.get(targetId);\n```\n\n데이터가 수천 건일 때, `Array.includes()`의 **O(n)**과 `Set.has()`의 **O(1)** 차이는 체감 성능에 직접적으로 영향을 줍니다. 캐시 테이블, id 기반 lookup, 중복 제거 — 이 모든 패턴이 해시 테이블 원리예요."
  },
  {
    "id": 10,
    "question": "스택과 큐를 웹 개발과 연결해서 설명해주세요.",
    "answer": "**스택**은 접시 쌓기, **큐**는 줄 서기예요.\n\n```\n Stack (LIFO)        Queue (FIFO)\n ┌───┐               ┌───┬───┬───┐\n │ C │ ← pop         │ A │ B │ C │ → dequeue\n │ B │         enqueue→           \n │ A │\n └───┘\n 나중에 넣은 게 먼저   먼저 넣은 게 먼저\n```\n\n### 스택 (LIFO — Last In, First Out)\n\n가장 직접적인 예가 JavaScript의 **콜 스택**이에요. 함수가 호출되면 스택에 쌓이고, 실행이 끝나면 위에서부터 제거됩니다. 재귀 호출도 스택에 프레임이 계속 쌓이는 것이고, 너무 깊으면 **stack overflow**가 나요.\n\n웹에서 스택 구조의 예시:\n- 브라우저 **뒤로 가기** 히스토리\n- **Undo** 기능\n- 콜 스택\n\n### 큐 (FIFO — First In, First Out)\n\n**이벤트 루프**에서 **태스크 큐**가 대표적이에요. setTimeout 콜백이나 이벤트 핸들러가 큐에 순서대로 들어가고, 콜 스택이 비었을 때 앞에서부터 하나씩 꺼내서 실행합니다.\n\n웹에서 큐 구조의 예시:\n- **태스크 큐**, **마이크로태스크 큐**\n- 파일 업로드 대기열\n- 토스트 메시지 순차 표시\n\n프론트엔드에서 특히 이벤트 루프를 이해할 때, **콜 스택(Stack)**과 **태스크 큐(Queue)**, **마이크로태스크 큐**의 관계를 알아야 비동기 코드의 실행 순서를 정확히 예측할 수 있습니다."
  },
  {
    "id": 11,
    "question": "트리와 그래프의 차이를 설명해주세요.",
    "answer": "**트리**는 **그래프**의 특수한 형태예요. 가족 족보처럼 계층 구조를 가지고, 하나의 **루트 노드**에서 시작해서 위에서 아래로 뻗어나갑니다. **사이클(순환)이 없고**, 부모에서 자식으로 가는 단방향 관계가 명확해요.\n\n**그래프**는 더 일반적인 개념으로, 노드와 간선으로 연결됩니다. 방향이 있을 수도 없을 수도 있고, **사이클도 허용**돼요. 지하철 노선도가 그래프의 좋은 예입니다.\n\n```\n트리:                  그래프:\n     A                  A ←→ B\n    / \\                 ↑   / ↑\n   B   C                │  ↓  │\n  / \\                   D ←→ C\n D   E\n (사이클 없음)          (사이클 가능)\n```\n\n### 프론트엔드에서의 연결\n\n**트리 구조**는 매우 익숙해요:\n- **DOM** 트리\n- **React 컴포넌트** 트리\n- 라우팅 구조\n- 파일/폴더 구조\n\n**그래프 구조**는:\n- 번들러의 모듈 **dependency graph**\n- 웹사이트 간 링크 구조\n- 소셜 네트워크의 친구 관계\n\n모듈 A가 B를 참조하고, B가 C를 참조하고, C가 다시 A를 참조하는 **순환 의존(circular dependency)** 같은 문제도 그래프 관점에서 이해해야 합니다. 이 차이를 알면 DOM 순회, 컴포넌트 렌더링 순서, 의존성 분석 같은 문제를 더 구조적으로 사고할 수 있어요."
  },
  {
    "id": 12,
    "question": "시간복잡도와 공간복잡도를 설명하고, 실무에서 어떤 게 더 중요한가요?",
    "answer": "**시간복잡도**는 입력 크기에 따라 실행 시간이 어떻게 증가하는지, **공간복잡도**는 필요한 메모리가 어떻게 증가하는지를 **Big-O 표기법**으로 나타냅니다.\n\n| 표기 | 이름 | 프론트엔드 예시 |\n|---|---|---|\n| **O(1)** | 상수 | `Map.get()`, 배열 인덱스 접근 |\n| **O(log n)** | 로그 | 이진 탐색 |\n| **O(n)** | 선형 | 배열 순회, `Array.includes()` |\n| **O(n log n)** | 선형 로그 | `Array.sort()` |\n| **O(n²)** | 이차 | 이중 중첩 루프 |\n\n```\n시간 ↑\n     │    O(n²)\n     │   /\n     │  / O(n log n)\n     │ / /\n     │//  O(n)\n     │/ ──── O(log n)\n     └──────── O(1)\n          n →\n```\n\n### 실무에서 뭐가 더 중요한가?\n\n\"시간복잡도가 더 중요합니다\"라고 단정하기보다, **병목이 어디 있느냐에 따라 우선순위가 달라져요**.\n\n- **검색 자동완성**처럼 빠른 응답이 필요하면 → 시간복잡도 우선\n- **모바일 환경**이나 이미지 캐시 앱에서는 → 공간복잡도를 더 신경\n- **SPA를 오래 열어두는 경우** → 메모리 누수가 치명적 (공간)\n- **수천 행 테이블 렌더링** → 둘 다 중요\n\n데이터 크기와 기기 성능, UX 요구사항에 따라 실제 병목을 **측정해서 판단**하는 게 정확한 답이에요."
  },
  {
    "id": 13,
    "question": "퀵 정렬과 병합 정렬의 차이를 설명해주세요.",
    "answer": "둘 다 **분할 정복(Divide and Conquer)** 전략을 쓰지만, 특성이 꽤 달라요.\n\n### 퀵 정렬 (Quick Sort)\n\n**pivot**을 하나 골라서 작은 값과 큰 값으로 나눈 뒤 각각을 다시 정렬합니다. 평균적으로 매우 빠르고 **추가 메모리를 적게** 씁니다. 하지만 pivot 선택이 나쁘면 최악 **O(n²)**까지 갈 수 있어요.\n\n### 병합 정렬 (Merge Sort)\n\n배열을 반으로 나눈 뒤 정렬하고 합치는 방식. 항상 **O(n log n)**을 보장하는 안정적인 성능이 강점이에요. **stable sort**라서 같은 값의 원래 순서가 유지됩니다. 다만 합치는 과정에서 **추가 메모리**가 필요해요.\n\n| | 퀵 정렬 | 병합 정렬 |\n|---|---|---|\n| **평균** | O(n log n) | O(n log n) |\n| **최악** | O(n²) | O(n log n) |\n| **안정 정렬** | 아니오 | 예 |\n| **추가 메모리** | O(log n) | O(n) |\n| **강점** | 실용 성능, 메모리 효율 | 예측 가능성, 안정성 |\n\n프론트엔드에서 직접 정렬 알고리즘을 구현할 일은 적지만, 알아야 할 감각이 있어요:\n\n- **정렬 비용이 O(n log n)**이라는 인식 — 데이터가 커지면 정렬만으로도 프레임이 밀릴 수 있음\n- **stable sort가 필요한 상황** 판단 — 이미 정렬된 리스트에 추가 기준으로 재정렬할 때\n- JavaScript의 `Array.sort()`는 엔진마다 구현이 다르지만 대부분 **TimSort(병합 정렬 기반)**로 stable"
  },
  {
    "id": 14,
    "question": "데이터베이스에서 인덱스가 왜 필요한가요?",
    "answer": "**인덱스**는 책의 색인(찾아보기)과 같아요. 색인이 없으면 원하는 내용을 찾으려고 책을 처음부터 끝까지 넘겨야 하는데, 색인이 있으면 해당 페이지로 바로 갈 수 있죠.\n\n데이터베이스에서도 마찬가지입니다. 인덱스가 없으면 조건 검색 시 테이블 전체를 훑는 **풀 스캔(Full Scan)**이 필요하고, 인덱스가 있으면 정렬된 구조(주로 **B-Tree**)를 통해 필요한 범위를 훨씬 빠르게 찾아갈 수 있어요.\n\n### 하지만 인덱스는 공짜가 아닙니다\n\n| | 장점 | 비용 |\n|---|---|---|\n| **읽기** | 조회 속도 대폭 향상 | - |\n| **쓰기** | - | INSERT, UPDATE, DELETE 시 인덱스도 갱신 |\n| **저장** | - | 추가 저장 공간 필요 |\n\n그래서 **자주 조회하는 컬럼**에는 인덱스를 걸고, **자주 변경되는 컬럼**에는 신중하게 판단해야 해요.\n\n### 프론트엔드 개발자도 알아야 하는 이유\n\n검색이나 필터 API가 느릴 때, 프론트만 의심할 게 아니라 **백엔드의 DB 인덱스 설계가 병목**일 수 있다는 감각이 있으면 더 효과적으로 소통할 수 있습니다. \"이 API가 느린데, WHERE 절에 사용하는 컬럼에 인덱스가 있나요?\"라고 물어볼 수 있으면 협업 효율이 크게 달라져요."
  },
  {
    "id": 15,
    "question": "정규화와 비정규화의 개념을 설명해주세요.",
    "answer": "**정규화**는 데이터 중복을 줄이기 위해 역할별로 테이블을 분리하는 과정이에요. 비유하면, 모든 정보를 한 장의 엑셀 시트에 넣는 대신, 사용자 시트와 주문 시트를 따로 만들어서 관리하는 거예요.\n\n**비정규화**는 반대로, 조회 성능을 위해 일부 중복을 의도적으로 허용하는 전략입니다.\n\n### 비교\n\n| | 정규화 | 비정규화 |\n|---|---|---|\n| **중복** | 최소화 | 일부 허용 |\n| **일관성** | 높음 (수정 시 한 곳만) | 관리 어려움 |\n| **조회** | JOIN 필요 → 복잡할 수 있음 | 한 테이블에서 바로 → 빠름 |\n| **적합한 경우** | 쓰기가 많은 시스템 | 읽기가 많은 시스템 |\n\n예를 들어, 사용자 정보와 주문 정보를 하나의 테이블에 넣으면 사용자 이름이 주문마다 반복되겠죠. 이름을 바꾸려면 모든 주문 행을 다 수정해야 해요. 별도 테이블로 나누면(정규화) 한 곳만 바꾸면 됩니다.\n\n하지만 읽기가 압도적으로 많고 쓰기가 적은 경우에는, JOIN 비용을 줄이기 위해 의도적으로 데이터를 합쳐놓기도 해요(비정규화).\n\n### 프론트엔드에서의 연결\n\n실무에서 **상태 구조**를 설계할 때도 비슷한 판단을 합니다. **Redux**에서 엔티티를 id 기반으로 정규화해서 관리하는 패턴이 대표적이에요. `{ byId: { 1: {...}, 2: {...} }, allIds: [1, 2] }` 같은 구조가 바로 정규화된 상태입니다."
  },
  {
    "id": 16,
    "question": "트랜잭션의 ACID를 설명해주세요.",
    "answer": "**ACID**는 트랜잭션(하나의 작업 단위)이 신뢰할 수 있으려면 갖춰야 하는 네 가지 속성이에요.\n\n### 네 가지 속성\n\n**A — Atomicity (원자성)**\n트랜잭션 안의 작업이 **전부 성공하거나 전부 실패**해야 합니다. 절반만 반영되는 상태는 안 돼요. \"올인 아니면 올아웃\"이라고 생각하면 됩니다.\n\n**C — Consistency (일관성)**\n트랜잭션 전후로 데이터베이스의 **무결성 규칙이 유지**되어야 합니다.\n\n**I — Isolation (격리성)**\n동시에 실행되는 트랜잭션들이 **서로 간섭하지 않도록** 합니다.\n\n**D — Durability (지속성)**\n커밋된 결과가 시스템 장애가 나더라도 **영구적으로 유지**됩니다.\n\n### 실무 예시\n\n온라인 쇼핑에서 주문을 생성하면:\n1. 결제 기록 생성\n2. 재고 차감\n3. 주문 기록 생성\n\n이 세 가지가 하나의 트랜잭션이에요. 결제는 됐는데 재고 차감이 실패하면 데이터가 꼬이니까, 하나라도 실패하면 전부 **롤백(rollback)**되어야 합니다.\n\n### 프론트엔드와의 연결\n\n직접 DB 트랜잭션을 다루진 않지만, **optimistic update 후 롤백 설계**나 여러 API를 순차 호출할 때 일관성을 유지하는 문제가 ACID와 같은 맥락이에요. React 19의 **useOptimistic**이 서버 실패 시 자동 롤백하는 것도 원자성 개념의 UI 버전이라고 볼 수 있습니다."
  },
  {
    "id": 17,
    "question": "CAP 이론이 무엇인가요?",
    "answer": "**CAP 이론**은 분산 시스템에서 세 가지 속성을 **동시에 완벽하게 만족시키기 어렵다**는 설명이에요.\n\n### 세 가지 속성\n\n- **C — Consistency (일관성)**: 모든 노드가 같은 시점에 같은 데이터를 본다\n- **A — Availability (가용성)**: 요청에 항상 응답할 수 있다\n- **P — Partition Tolerance (분할 내성)**: 네트워크가 끊어져도 시스템이 계속 동작한다\n\n```\n        C (일관성)\n       / \\\n      /   \\\n     /     \\\n    A ───── P\n  (가용성)  (분할 내성)\n\n  분산 환경에서는 P를 포기할 수 없으므로\n  실질적으로 C와 A 사이의 trade-off\n```\n\n### 핵심 포인트\n\n\"항상 셋 중 둘만 선택 가능하다\"처럼 기계적으로 말하면 정확하지 않아요. 분산 환경에서는 네트워크 분할을 완전히 피할 수 없기 때문에(**P는 필수**), 실질적으로는 **일관성과 가용성 사이에서 균형**을 잡아야 합니다.\n\n- **CP 시스템**: 일관성 우선 → 네트워크 분할 시 일부 요청 거부 (예: 은행 시스템)\n- **AP 시스템**: 가용성 우선 → 일시적으로 데이터가 다를 수 있음 (예: SNS 피드)\n\nCAP을 절대적인 규칙이 아니라, **분산 시스템의 trade-off를 이해하는 사고 틀**로 받아들이는 게 더 정확합니다."
  },
  {
    "id": 18,
    "question": "캐시가 왜 성능을 높이는지 설명해주세요.",
    "answer": "**캐시**는 한마디로 **\"자주 쓰는 걸 가까이 두기\"**예요. 매번 먼 원본 서버까지 가지 않고, 이미 가져온 데이터를 재사용해서 지연 시간을 줄이는 겁니다.\n\n### 프론트엔드에서 캐시가 작동하는 층\n\n```\n요청 흐름:\n브라우저 메모리 캐시 → 디스크 캐시 → CDN → 원본 서버\n  (가장 빠름)                              (가장 느림)\n\n각 층에서 캐시 히트하면 그 이상 안 감\n```\n\n| 캐시 종류 | 역할 | 예시 |\n|---|---|---|\n| **브라우저 캐시** | 정적 리소스 재다운로드 방지 | JS 번들, CSS, 이미지 |\n| **CDN 캐시** | 지리적으로 가까운 서버에서 응답 | 전 세계 사용자 대상 서비스 |\n| **API 응답 캐시** | 이전 데이터 먼저 보여주고 백그라운드 갱신 | React Query의 **stale-while-revalidate** |\n| **서버 사이드 캐시** | 서버에서 렌더링 결과나 DB 쿼리 캐시 | Next.js Data Cache |\n\n### 주의할 점\n\n캐시가 만능은 아니에요. **캐시 무효화(invalidation)** 전략을 잘 설계하지 않으면 오래된 데이터가 보이는 문제가 생깁니다. 컴퓨터 과학에서 \"캐시 무효화는 가장 어려운 문제 중 하나\"라는 말이 있을 정도예요.\n\n- **TTL(Time To Live)**: 일정 시간 후 캐시 만료\n- **revalidation**: 백그라운드에서 최신 데이터 확인\n- **cache busting**: 파일명에 해시를 넣어 강제 갱신 (예: `app.a1b2c3.js`)\n\n핵심은 **원본 접근을 줄이고 이미 가져온 데이터를 재사용**하는 것이며, 무효화 정책도 함께 설계해야 해요."
  },
  {
    "id": 19,
    "question": "프론트엔드 개발자도 CS 지식을 알아야 하는 이유는 무엇인가요?",
    "answer": "프론트엔드는 단순히 화면만 그리는 역할이 아니에요. **비동기 처리, 상태 일관성, 렌더링 비용, 메모리 관리, 네트워크 실패**까지 다루는 직무입니다. 이 모든 문제가 CS 개념과 직접 연결돼요.\n\n### CS 개념별 프론트엔드 연결\n\n| CS 개념 | 프론트엔드 문제 |\n|---|---|\n| **Race Condition** | 오래된 API 응답이 최신 UI를 덮어쓰는 버그 |\n| **자료구조 + 시간복잡도** | 대용량 리스트 성능 병목 진단 |\n| **메모리 + GC** | 이벤트 리스너 누수, 클로저로 인한 메모리 증가 |\n| **이벤트 루프** | setTimeout이 왜 즉시가 아닌지, UI가 왜 멈추는지 |\n| **스택 + 큐** | 콜 스택 오버플로우, 태스크 큐 실행 순서 |\n| **캐시** | API 응답 캐시 전략, stale-while-revalidate |\n| **해시 테이블** | Set/Map으로 O(n)을 O(1)로 최적화 |\n\nCS를 알아야 하는 진짜 이유는 **문제를 정확히 설명하고, 원인을 구분하고, 구조적으로 해결할 수 있기 때문**이에요.\n\n\"가끔 데이터가 이상해요\"를 → \"검색 자동완성에서 race condition이 발생해서, AbortController로 이전 요청을 취소하겠습니다\"로 바꿀 수 있는 게 CS 지식의 힘입니다.\n\n구현력도 중요하지만, **개념적 이해가 유지보수 품질과 디버깅 능력을 훨씬 더 크게 좌우**한다고 생각해요."
  }
]
